accelbyte_py_sdk/api/dsartifact/__init__.py
accelbyte_py_sdk/api/dsartifact/errors.py
accelbyte_py_sdk/api/dsartifact/models/__init__.py
accelbyte_py_sdk/api/dsartifact/models/log_app_message_declaration.py
accelbyte_py_sdk/api/dsartifact/models/models_all_queue_result.py
accelbyte_py_sdk/api/dsartifact/models/models_artifact_file_status.py
accelbyte_py_sdk/api/dsartifact/models/models_list_all_queue_response.py
accelbyte_py_sdk/api/dsartifact/models/models_list_nodes_ip_address.py
accelbyte_py_sdk/api/dsartifact/models/models_list_queue_response.py
accelbyte_py_sdk/api/dsartifact/models/models_list_terminated_servers_response.py
accelbyte_py_sdk/api/dsartifact/models/models_match_result.py
accelbyte_py_sdk/api/dsartifact/models/models_notif_payload_server_status_change.py
accelbyte_py_sdk/api/dsartifact/models/models_paging_cursor.py
accelbyte_py_sdk/api/dsartifact/models/models_queue.py
accelbyte_py_sdk/api/dsartifact/models/models_queue_result.py
accelbyte_py_sdk/api/dsartifact/models/models_request_match_member.py
accelbyte_py_sdk/api/dsartifact/models/models_request_match_party.py
accelbyte_py_sdk/api/dsartifact/models/models_request_matching_ally.py
accelbyte_py_sdk/api/dsartifact/models/models_server.py
accelbyte_py_sdk/api/dsartifact/models/models_status_history.py
accelbyte_py_sdk/api/dsartifact/models/response_error.py
accelbyte_py_sdk/api/dsartifact/operations/__init__.py
accelbyte_py_sdk/api/dsartifact/operations/all_terminated_servers/__init__.py
accelbyte_py_sdk/api/dsartifact/operations/all_terminated_servers/list_terminated_servers.py
accelbyte_py_sdk/api/dsartifact/operations/artifact_upload_process_queue/__init__.py
accelbyte_py_sdk/api/dsartifact/operations/artifact_upload_process_queue/delete_active_queue.py
accelbyte_py_sdk/api/dsartifact/operations/artifact_upload_process_queue/delete_node_by_id.py
accelbyte_py_sdk/api/dsartifact/operations/artifact_upload_process_queue/delete_queue.py
accelbyte_py_sdk_service_dsartifact-0.16.0.dist-info/METADATA
accelbyte_py_sdk_service_dsartifact-0.16.0.dist-info/WHEEL
accelbyte_py_sdk_service_dsartifact-0.16.0.dist-info/top_level.txt
accelbyte_py_sdk_service_dsartifact-0.16.0.dist-info/RECORD
