Metadata-Version: 2.4
Name: accelbyte-py-sdk-service-dsartifact
Version: 0.16.0
Summary: AccelByte Python SDK - AccelByte Gaming Services Ds Artifact Manager
Requires-Python: >=3.9
Requires-Dist: accelbyte-py-sdk-core
